athreading/__init__.py
athreading/aliases.py
athreading/callable.py
athreading/callback_iterator.py
athreading/callback_single.py
athreading/generator.py
athreading/iterator.py
athreading/py.typed
athreading-0.3.0.dist-info/METADATA
athreading-0.3.0.dist-info/WHEEL
athreading-0.3.0.dist-info/licenses/LICENSE
athreading-0.3.0.dist-info/RECORD
