Metadata-Version: 2.4
Name: athreading
Version: 0.3.0
Summary: Asynchronous threading package for Python
License-Expression: BSD-3-Clause
License-File: LICENSE
Author: Callan Gray
Author-email: cal.j.gray@gmail.com
Requires-Python: >=3.9
Classifier: Framework :: AsyncIO
Classifier: Programming Language :: Python :: 3
Classifier: Programming Language :: Python :: 3.9
Classifier: Programming Language :: Python :: 3.10
Classifier: Programming Language :: Python :: 3.11
Classifier: Programming Language :: Python :: 3.12
Classifier: Programming Language :: Python :: 3.13
Classifier: Programming Language :: Python :: 3.14
Classifier: Typing :: Typed
Project-URL: Homepage, https://github.com/calgray/athreading
Project-URL: Repository, https://github.com/calgray/athreading.git
